LICENSE
README.md
setup.py
adia/__init__.py
adia/canvas.py
adia/constants.py
adia/container.py
adia/diagram.py
adia/exceptions.py
adia/interpreter.py
adia/lazyattr.py
adia/mutablestring.py
adia/renderer.py
adia/renderingplans.py
adia/sequence.py
adia/token.py
adia/tokenizer.py
adia.egg-info/PKG-INFO
adia.egg-info/SOURCES.txt
adia.egg-info/dependency_links.txt
adia.egg-info/entry_points.txt
adia.egg-info/requires.txt
adia.egg-info/top_level.txt
adiacli/__init__.py
adiacli/main.py